pychrome/__init__.py
pychrome/browser.py
pychrome/cli.py
pychrome/exceptions.py
pychrome/tab.py
cc12703_pychrome-0.2.6.dist-info/LICENSE
cc12703_pychrome-0.2.6.dist-info/METADATA
cc12703_pychrome-0.2.6.dist-info/WHEEL
cc12703_pychrome-0.2.6.dist-info/entry_points.txt
cc12703_pychrome-0.2.6.dist-info/top_level.txt
cc12703_pychrome-0.2.6.dist-info/RECORD
