Metadata-Version: 2.1
Name: cc12703-pychrome
Version: 0.2.6
Summary: A Python Package for the Google Chrome Dev Protocol
Home-page: https://github.com/cc12703/pychrome
Author: fate0
Author-email: fate0@fatezero.org
License: BSD license
Keywords: pychrome
Platform: UNKNOWN
Classifier: Development Status :: 5 - Production/Stable
Classifier: Intended Audience :: Developers
Classifier: License :: OSI Approved :: BSD License
Classifier: Natural Language :: English
Classifier: Programming Language :: Python :: 2.7
Classifier: Programming Language :: Python :: 3.4
Classifier: Programming Language :: Python :: 3.5
Classifier: Programming Language :: Python :: 3.6
Classifier: Topic :: Internet :: WWW/HTTP
Classifier: Topic :: Internet :: WWW/HTTP :: Browsers
Requires-Dist: click (>=6.0)
Requires-Dist: websocket-client (>=0.44.0)
Requires-Dist: requests (>=2.13.0)
